{
  "version": "7",
  "dialect": "postgresql",
  "entries": [
    {
      "idx": 0,
      "version": "7",
      "when": 1782460411869,
      "tag": "0000_peaceful_nighthawk",
      "breakpoints": true
    },
    {
      "idx": 1,
      "version": "7",
      "when": 1782464643584,
      "tag": "0001_secret_menace",
      "breakpoints": true
    },
    {
      "idx": 2,
      "version": "7",
      "when": 1782470809328,
      "tag": "0002_wet_marvel_apes",
      "breakpoints": true
    },
    {
      "idx": 3,
      "version": "7",
      "when": 1782483726068,
      "tag": "0003_cute_komodo",
      "breakpoints": true
    },
    {
      "idx": 4,
      "version": "7",
      "when": 1782503740636,
      "tag": "0004_natural_leper_queen",
      "breakpoints": true
    },
    {
      "idx": 5,
      "version": "7",
      "when": 1782510526679,
      "tag": "0005_fixed_fenris",
      "breakpoints": true
    },
    {
      "idx": 6,
      "version": "7",
      "when": 1782590985073,
      "tag": "0006_nifty_omega_sentinel",
      "breakpoints": true
    },
    {
      "idx": 7,
      "version": "7",
      "when": 1782596017478,
      "tag": "0007_clear_shockwave",
      "breakpoints": true
    },
    {
      "idx": 8,
      "version": "7",
      "when": 1782749068085,
      "tag": "0008_bizarre_fabian_cortez",
      "breakpoints": true
    },
    {
      "idx": 9,
      "version": "7",
      "when": 1782754053883,
      "tag": "0009_polite_rattler",
      "breakpoints": true
    }
  ]
}